erpipc/__init__.py
erpipc/file_hand.py
erpipc/initial_structure.py
erpipc/ions_jumping_process.py
erpipc/parameter_calculation.py
erpipc/samples_to_generate.py
erpipc-0.1.1.dist-info/METADATA
erpipc-0.1.1.dist-info/WHEEL
erpipc-0.1.1.dist-info/entry_points.txt
erpipc-0.1.1.dist-info/top_level.txt
erpipc-0.1.1.dist-info/RECORD
