Metadata-Version: 2.1
Name: erpipc
Version: 0.1.1
Summary: UNKNOWN
Home-page: https://gitee.com/shuhebing/erpipc
Author: Ding Yuqing
Author-email: 1024670883@qq.com
License: UNKNOWN
Platform: UNKNOWN
Requires-Python: >=3.7,<3.10
